[
    {
        "id": "2d6c2720e858c77e",
        "type": "tab",
        "label": "TTN",
        "disabled": false,
        "info": "",
        "env": []
    },
    {
        "id": "99673ca2acc219cd",
        "type": "mqtt in",
        "z": "2d6c2720e858c77e",
        "name": "",
        "topic": "#",
        "qos": "1",
        "datatype": "json",
        "broker": "e066e6bf72cf86c2",
        "nl": false,
        "rap": true,
        "rh": 0,
        "inputs": 0,
        "x": 210,
        "y": 260,
        "wires": [
            [
                "191f8092769f2146",
                "191f8092769f2146"
            ]
        ]
    },
    {
        "id": "27d87904352cb1d0",
        "type": "debug",
        "z": "2d6c2720e858c77e",
        "name": "",
        "active": true,
        "tosidebar": true,
        "console": false,
        "tostatus": false,
        "complete": "payload",
        "targetType": "msg",
        "statusVal": "",
        "statusType": "auto",
        "x": 770,
        "y": 80,
        "wires": []
    },
    {
        "id": "191f8092769f2146",
        "type": "json",
        "z": "2d6c2720e858c77e",
        "name": "",
        "property": "payload",
        "action": "obj",
        "pretty": true,
        "x": 350,
        "y": 260,
        "wires": [
            [
                "b5e7e5f9cdf1601e",
                "b5e7e5f9cdf1601e"
            ]
        ]
    },
    {
        "id": "b5e7e5f9cdf1601e",
        "type": "function",
        "z": "2d6c2720e858c77e",
        "name": "decoder",
        "func": "var msg0 = { payload: msg.payload.uplink_message.decoded_payload.concentration };\nvar msg1 = { payload: msg.payload.uplink_message.decoded_payload.humidite };\nvar msg2 = { payload: msg.payload.uplink_message.decoded_payload.temperature };\n\nreturn [msg0, msg1, msg2];",
        "outputs": 3,
        "noerr": 0,
        "initialize": "",
        "finalize": "",
        "libs": [],
        "x": 520,
        "y": 260,
        "wires": [
            [
                "27d87904352cb1d0",
                "65e3d42fb50b732b",
                "27d87904352cb1d0",
                "65e3d42fb50b732b",
                "1efaa5014097d1b7"
            ],
            [
                "890d7807130a805a",
                "08ad31ea1606f2fa",
                "b35865ec593fbe87"
            ],
            [
                "d63b38d42c1998d5",
                "23d5800be0d230e5",
                "ecf4158c4fd9f31b"
            ]
        ]
    },
    {
        "id": "65e3d42fb50b732b",
        "type": "ui_chart",
        "z": "2d6c2720e858c77e",
        "name": "",
        "group": "67d19e362e8373fc",
        "order": 3,
        "width": 4,
        "height": 4,
        "label": "CO2",
        "chartType": "line",
        "legend": "false",
        "xformat": "HH:mm:ss",
        "interpolate": "linear",
        "nodata": "",
        "dot": false,
        "ymin": "",
        "ymax": "",
        "removeOlder": 1,
        "removeOlderPoints": "30",
        "removeOlderUnit": "3600",
        "cutout": 0,
        "useOneColor": false,
        "useUTC": false,
        "colors": [
            "#1f77b4",
            "#aec7e8",
            "#ff7f0e",
            "#2ca02c",
            "#98df8a",
            "#d62728",
            "#ff9896",
            "#9467bd",
            "#c5b0d5"
        ],
        "outputs": 1,
        "useDifferentColor": false,
        "className": "",
        "x": 770,
        "y": 140,
        "wires": [
            []
        ]
    },
    {
        "id": "1efaa5014097d1b7",
        "type": "ui_gauge",
        "z": "2d6c2720e858c77e",
        "name": "",
        "group": "67d19e362e8373fc",
        "order": 6,
        "width": 4,
        "height": 4,
        "gtype": "gage",
        "title": "CO2",
        "label": "units",
        "format": "{{value}}",
        "min": 0,
        "max": "5000",
        "colors": [
            "#08fd51",
            "#00a841",
            "#035e1a"
        ],
        "seg1": "",
        "seg2": "",
        "className": "",
        "x": 770,
        "y": 200,
        "wires": []
    },
    {
        "id": "08ad31ea1606f2fa",
        "type": "ui_chart",
        "z": "2d6c2720e858c77e",
        "name": "",
        "group": "67d19e362e8373fc",
        "order": 2,
        "width": 4,
        "height": 4,
        "label": "Humidite",
        "chartType": "line",
        "legend": "false",
        "xformat": "HH:mm:ss",
        "interpolate": "linear",
        "nodata": "",
        "dot": false,
        "ymin": "",
        "ymax": "",
        "removeOlder": 1,
        "removeOlderPoints": "30",
        "removeOlderUnit": "3600",
        "cutout": 0,
        "useOneColor": false,
        "useUTC": false,
        "colors": [
            "#1f77b4",
            "#aec7e8",
            "#ff7f0e",
            "#2ca02c",
            "#98df8a",
            "#d62728",
            "#ff9896",
            "#9467bd",
            "#c5b0d5"
        ],
        "outputs": 1,
        "useDifferentColor": false,
        "className": "",
        "x": 780,
        "y": 280,
        "wires": [
            []
        ]
    },
    {
        "id": "b35865ec593fbe87",
        "type": "ui_gauge",
        "z": "2d6c2720e858c77e",
        "name": "",
        "group": "67d19e362e8373fc",
        "order": 5,
        "width": 4,
        "height": 4,
        "gtype": "gage",
        "title": "Humidite",
        "label": "units",
        "format": "{{value}}",
        "min": 0,
        "max": "100",
        "colors": [
            "#00ccff",
            "#4281ff",
            "#0011ff"
        ],
        "seg1": "",
        "seg2": "",
        "className": "",
        "x": 780,
        "y": 320,
        "wires": []
    },
    {
        "id": "890d7807130a805a",
        "type": "debug",
        "z": "2d6c2720e858c77e",
        "name": "",
        "active": true,
        "tosidebar": true,
        "console": false,
        "tostatus": false,
        "complete": "payload",
        "targetType": "msg",
        "statusVal": "",
        "statusType": "auto",
        "x": 790,
        "y": 240,
        "wires": []
    },
    {
        "id": "d63b38d42c1998d5",
        "type": "debug",
        "z": "2d6c2720e858c77e",
        "name": "",
        "active": true,
        "tosidebar": true,
        "console": false,
        "tostatus": false,
        "complete": "false",
        "x": 790,
        "y": 380,
        "wires": []
    },
    {
        "id": "23d5800be0d230e5",
        "type": "ui_chart",
        "z": "2d6c2720e858c77e",
        "name": "",
        "group": "67d19e362e8373fc",
        "order": 1,
        "width": 4,
        "height": 4,
        "label": "Temprature",
        "chartType": "line",
        "legend": "false",
        "xformat": "HH:mm:ss",
        "interpolate": "linear",
        "nodata": "",
        "dot": false,
        "ymin": "",
        "ymax": "",
        "removeOlder": 1,
        "removeOlderPoints": "30",
        "removeOlderUnit": "3600",
        "cutout": 0,
        "useOneColor": false,
        "useUTC": false,
        "colors": [
            "#1f77b4",
            "#aec7e8",
            "#ff7f0e",
            "#2ca02c",
            "#98df8a",
            "#d62728",
            "#ff9896",
            "#9467bd",
            "#c5b0d5"
        ],
        "outputs": 1,
        "useDifferentColor": false,
        "className": "",
        "x": 790,
        "y": 422,
        "wires": [
            []
        ]
    },
    {
        "id": "ecf4158c4fd9f31b",
        "type": "ui_gauge",
        "z": "2d6c2720e858c77e",
        "name": "",
        "group": "67d19e362e8373fc",
        "order": 4,
        "width": 4,
        "height": 4,
        "gtype": "gage",
        "title": "Temperature",
        "label": "units",
        "format": "{{value}}",
        "min": "-10",
        "max": "40",
        "colors": [
            "#80ff80",
            "#00b850",
            "#eeff00"
        ],
        "seg1": "",
        "seg2": "",
        "className": "",
        "x": 790,
        "y": 480,
        "wires": []
    },
    {
        "id": "b12f00ecc8360be0",
        "type": "debug",
        "z": "2d6c2720e858c77e",
        "name": "",
        "active": true,
        "tosidebar": true,
        "console": false,
        "tostatus": false,
        "complete": "false",
        "x": 450,
        "y": 380,
        "wires": []
    },
    {
        "id": "d9e1615fb2f83c8e",
        "type": "ui_chart",
        "z": "2d6c2720e858c77e",
        "name": "",
        "group": "67d19e362e8373fc",
        "order": 3,
        "width": 4,
        "height": 4,
        "label": "CO2_sec",
        "chartType": "line",
        "legend": "false",
        "xformat": "HH:mm:ss",
        "interpolate": "linear",
        "nodata": "",
        "dot": false,
        "ymin": "",
        "ymax": "",
        "removeOlder": 1,
        "removeOlderPoints": "30",
        "removeOlderUnit": "3600",
        "cutout": 0,
        "useOneColor": false,
        "useUTC": false,
        "colors": [
            "#1f77b4",
            "#aec7e8",
            "#ff7f0e",
            "#2ca02c",
            "#98df8a",
            "#d62728",
            "#ff9896",
            "#9467bd",
            "#c5b0d5"
        ],
        "outputs": 1,
        "useDifferentColor": false,
        "className": "",
        "x": 460,
        "y": 440,
        "wires": [
            []
        ]
    },
    {
        "id": "4118c60d54815ee0",
        "type": "ui_gauge",
        "z": "2d6c2720e858c77e",
        "name": "",
        "group": "67d19e362e8373fc",
        "order": 6,
        "width": 4,
        "height": 4,
        "gtype": "gage",
        "title": "CO2_sec",
        "label": "units",
        "format": "{{value}}",
        "min": 0,
        "max": "5000",
        "colors": [
            "#08fd51",
            "#00a841",
            "#035e1a"
        ],
        "seg1": "",
        "seg2": "",
        "className": "",
        "x": 440,
        "y": 500,
        "wires": []
    },
    {
        "id": "8fa35262a149c745",
        "type": "mqtt in",
        "z": "2d6c2720e858c77e",
        "name": "",
        "topic": "esp32/co2",
        "qos": "2",
        "datatype": "auto",
        "broker": "10e78a89.5b4fd5",
        "nl": false,
        "rap": false,
        "inputs": 0,
        "x": 240,
        "y": 460,
        "wires": [
            [
                "b12f00ecc8360be0",
                "d9e1615fb2f83c8e",
                "4118c60d54815ee0"
            ]
        ]
    },
    {
        "id": "e066e6bf72cf86c2",
        "type": "mqtt-broker",
        "name": "TTN",
        "broker": "eu1.cloud.thethings.network",
        "port": "1883",
        "clientid": "",
        "autoConnect": true,
        "usetls": false,
        "protocolVersion": "4",
        "keepalive": "60",
        "cleansession": true,
        "birthTopic": "",
        "birthQos": "0",
        "birthPayload": "",
        "birthMsg": {},
        "closeTopic": "",
        "closeQos": "0",
        "closePayload": "",
        "closeMsg": {},
        "willTopic": "",
        "willQos": "0",
        "willPayload": "",
        "willMsg": {},
        "sessionExpiry": ""
    },
    {
        "id": "67d19e362e8373fc",
        "type": "ui_group",
        "name": "TTN",
        "tab": "e7c46d5e.a1283",
        "order": 2,
        "disp": true,
        "width": "12",
        "collapse": false,
        "className": ""
    },
    {
        "id": "10e78a89.5b4fd5",
        "type": "mqtt-broker",
        "name": "",
        "broker": "localhost",
        "port": "1883",
        "clientid": "",
        "autoConnect": true,
        "usetls": false,
        "protocolVersion": "4",
        "keepalive": "60",
        "cleansession": true,
        "birthTopic": "",
        "birthQos": "0",
        "birthPayload": "",
        "birthMsg": {},
        "closeTopic": "",
        "closeQos": "0",
        "closePayload": "",
        "closeMsg": {},
        "willTopic": "",
        "willQos": "0",
        "willPayload": "",
        "willMsg": {},
        "sessionExpiry": ""
    },
    {
        "id": "e7c46d5e.a1283",
        "type": "ui_tab",
        "name": "Home Dashboard",
        "icon": "dashboard",
        "disabled": false,
        "hidden": false
    }
]